Metadata-Version: 2.3
Name: mkdocstrings-matlab-r2023a
Version: 0.1.2
Summary: Add your description here
Project-URL: Documentation, http://watermarkhu.nl/mkdocstrings-matlab/
Project-URL: Repository, https://github.com/watermarkhu/mkdocstrings-matlab-r2023a
Project-URL: Issues, https://github.com/watermarkhu/mkdocstrings-matla-r2023a/issues
Author-email: Mark Shui Hu <watermarkhu@gmail.com>
License: MIT License
License-File: LICENSE
Keywords: docstring,documentation,matlab,mkdocs,mkdocstrings
Classifier: Development Status :: 3 - Alpha
Classifier: Intended Audience :: Developers
Classifier: License :: OSI Approved :: MIT License
Classifier: Programming Language :: Python :: 3
Classifier: Programming Language :: Python :: 3.8
Classifier: Programming Language :: Python :: 3.9
Classifier: Programming Language :: Python :: 3.10
Classifier: Topic :: Software Development :: Documentation
Requires-Python: <3.11,>=3.8
Requires-Dist: matlabengine==9.14.7
